pyutils/__init__.py
pyutils/gen_test_report.py
pyutils/extender/__init__.py
pyutils/extender/constants.py
pyutils/extender/framework/__init__.py
pyutils/extender/framework/config.py
pyutils/extender/framework/context.py
pyutils/extender/framework/context_test.py
pyutils/extender/framework/error.py
pyutils/extender/framework/framework.py
pyutils/extender/framework/interface.py
pyutils/extender/plugins/__init__.py
pyutils/extender/plugins/commands/__init__.py
pyutils/extender/plugins/commands/env.py
pyutils/extender/plugins/commands/generic.py
pyutils/extender/plugins/components/__init__.py
pyutils/extender/plugins/components/env_provider.py
pyutils/extender/plugins/services/__init__.py
pyutils/extender/plugins/services/cache_service.py
pyutils/extender/plugins/services/cache_service_test.py
pyutils/extender/plugins/services/generic_service.py
pyutils/extender/plugins/services/events/__init__.py
pyutils/extender/plugins/services/events/cache_events.py
pyutils/hadoop/__init__.py
pyutils/hadoop/conf.py
pyutils/io/__init__.py
pyutils/io/file.py
pyutils/io/git_repo.py
pyutils/io/git_repo_test.py
pyutils/io/mail_reader.py
pyutils/io/mail_sender.py
pyutils/io/pandas.py
pyutils/io/process_bar.py
pyutils/io/rest.py
pyutils/io/shell.py
pyutils/io/shell_test.py
pyutils/io/table.py
pyutils/processing/__init__.py
pyutils/processing/qps_calculator.py
pyutils/processing/timer.py
pyutils/scheduling/__init__.py
pyutils/scheduling/event_driven.py
pyutils/scheduling/event_driven_test.py
pyutils/scheduling/scheduler.py
pyutils/scheduling/scheduler_test.py
pyutils/structures/__init__.py
pyutils/structures/convert.py
pyutils/structures/dict.py
pyutils/structures/iterable.py
pyutils/structures/iterable_test.py
pyutils/structures/list.py
pyutils/structures/reflect.py
pyutils/structures/string.py
pyutils/structures/time.py
pyutils/structures/tuple.py
yolo_pyutils-0.1.54.dist-info/LICENSE
yolo_pyutils-0.1.54.dist-info/METADATA
yolo_pyutils-0.1.54.dist-info/WHEEL
yolo_pyutils-0.1.54.dist-info/top_level.txt
yolo_pyutils-0.1.54.dist-info/RECORD
