Metadata-Version: 2.1
Name: yolo-pyutils
Version: 0.1.54
Summary: yolo-pyutils provides utility functions for IO, data-processing, scheduling, common structures etc.
Home-page: https://github.com/TaoYang526/yolo-pyutils
Author: Tao Yang
Author-email: ytaofighting@gmail.com
License: Apache License 2.0
Keywords: utils
Classifier: Development Status :: 2 - Pre-Alpha
Classifier: Topic :: Utilities
Classifier: License :: OSI Approved :: Apache Software License
Classifier: Programming Language :: Python :: 3
License-File: LICENSE
